ezalpy/__init__.py
ezalpy/ezalpy.py
ezalpy/ezalpybeta.py
ezalpy-0.1.dist-info/LICENSE
ezalpy-0.1.dist-info/METADATA
ezalpy-0.1.dist-info/WHEEL
ezalpy-0.1.dist-info/top_level.txt
ezalpy-0.1.dist-info/RECORD
