Metadata-Version: 2.1
Name: ezalpy
Version: 0.1
Summary: Modul with System Extension and many more Features, available for Linux and Windows
Home-page: https://github.com/DevMasterLinux/al.py
Download-URL: https://github.com/DevMasterLinux/al.py/releases/download/0.1/file.tar.gz
Author: Kevin Alexander Krefting
Author-email: kakrefting@gmail.com
Maintainer: Kevin Alexander Krefting
Maintainer-email: kakrefting@gmail.com
License-File: LICENSE
